mkfeyndiag
setup.py
pyfeyn/__init__.py
pyfeyn/blobs.py
pyfeyn/config.py
pyfeyn/deco.py
pyfeyn/diagrams.py
pyfeyn/feynml.py
pyfeyn/hepnames.py
pyfeyn/lines.py
pyfeyn/paint.py
pyfeyn/points.py
pyfeyn/user.py
pyfeyn/utils.py
pyfeyn.egg-info/PKG-INFO
pyfeyn.egg-info/SOURCES.txt
pyfeyn.egg-info/dependency_links.txt
pyfeyn.egg-info/requires.txt
pyfeyn.egg-info/top_level.txt