Metadata-Version: 1.1
Name: pyfeyn
Version: 0.3.2
Summary: An easy-to-use Python library to help physicists draw Feynman diagrams.
Home-page: http://projects.hepforge.org/pyfeyn/
Author: ['Andy Buckley', 'Georg von Hippel']
Author-email: pyfeyn@projects.hepforge.org
License: GPL
Keywords: feynman hep physics particle diagram
Platform: UNKNOWN
Classifier: Development Status :: 4 - Beta
Classifier: Environment :: Console
Classifier: Intended Audience :: Science/Research
Classifier: License :: OSI Approved :: GNU General Public License (GPL)
Classifier: Operating System :: OS Independent
Classifier: Programming Language :: Python
Classifier: Topic :: Artistic Software
Classifier: Topic :: Scientific/Engineering :: Physics
